profidata/__init__.py
profidata/main.py
profidata-0.1.dist-info/licenses/LICENSE
profidata-0.1.dist-info/METADATA
profidata-0.1.dist-info/WHEEL
profidata-0.1.dist-info/top_level.txt
profidata-0.1.dist-info/RECORD
